pdf_mind/__init__.py
pdf_mind/agent.py
pdf_mind/config.py
pdf_mind/tools/__init__.py
pdf_mind/tools/image_extractor.py
pdf_mind/tools/pdf_reader.py
pdf_mind/tools/table_extractor.py
pdf_mind-0.1.2.dist-info/LICENSE
pdf_mind-0.1.2.dist-info/METADATA
pdf_mind-0.1.2.dist-info/WHEEL
pdf_mind-0.1.2.dist-info/entry_points.txt
pdf_mind-0.1.2.dist-info/RECORD
